fours/__init__.py
fours/detection_limits/__init__.py
fours/detection_limits/applefy_wrapper.py
fours/models/__init__.py
fours/models/noise.py
fours/models/normalization.py
fours/models/psf_subtraction.py
fours/models/rotation.py
fours/utils/__init__.py
fours/utils/adi_tools.py
fours/utils/data_handling.py
fours/utils/fwhm.py
fours/utils/logging.py
fours/utils/masks.py
fours/utils/pca.py
fours/utils/setups.py
fours-0.0.3.dist-info/LICENSE.txt
fours-0.0.3.dist-info/METADATA
fours-0.0.3.dist-info/WHEEL
fours-0.0.3.dist-info/top_level.txt
fours-0.0.3.dist-info/RECORD
