Metadata-Version: 2.1
Name: fours
Version: 0.0.3
Summary: Data post-processing for high-contrast imaging with the 4S Algorithm.
Home-page: https://github.com/markusbonse/fours.git
Author: Markus Bonse
Author-email: mbonse@phys.ethz.ch
License: MIT License
License-File: LICENSE.txt
Requires-Dist: seaborn
Requires-Dist: numpy
Requires-Dist: tqdm
Requires-Dist: photutils
Requires-Dist: matplotlib
Requires-Dist: scikit-learn
Requires-Dist: scikit-image
Requires-Dist: torch
Requires-Dist: h5py
Requires-Dist: astropy
Requires-Dist: tensorboard
Requires-Dist: pandas
Provides-Extra: dev
Requires-Dist: furo >=2022.12.7 ; extra == 'dev'
Requires-Dist: sphinx-rtd-theme ==1.1.1 ; extra == 'dev'
Requires-Dist: sphinx <6,>=2.1 ; extra == 'dev'
Requires-Dist: myst-parser ~=0.18.1 ; extra == 'dev'
Requires-Dist: nbsphinx >=0.8.9 ; extra == 'dev'
Requires-Dist: sphinx-copybutton ~=0.5.1 ; extra == 'dev'
Requires-Dist: sphinx-gallery <=0.10 ; extra == 'dev'
Requires-Dist: twine ~=4.0.2 ; extra == 'dev'
Requires-Dist: IPython ~=8.8.0 ; extra == 'dev'
Requires-Dist: ipywidgets ~=8.0.4 ; extra == 'dev'
Requires-Dist: jupyter-contrib-nbextensions ~=0.7.0 ; extra == 'dev'
Requires-Dist: sphinx-autodoc-typehints >1.6 ; extra == 'dev'
Provides-Extra: plotting
Requires-Dist: seaborn ~=0.12.1 ; extra == 'plotting'
Requires-Dist: matplotlib >=3.4.3 ; extra == 'plotting'
Requires-Dist: bokeh >=3.0.3 ; extra == 'plotting'
